{"_type":"export","__export_format":4,"__export_date":"2022-02-26T17:45:23.285Z","__export_source":"insomnia.desktop.app:v2021.7.2","resources":[{"_id":"req_622c1b6bd63941cb9a90158ee374a82f","parentId":"fld_9b1cc478b82d411b9b158e465f5c7ae0","modified":1645896700631,"created":1645802004521,"url":"localhost:5157/graphql","name":"Sorting Query","description":"","method":"POST","body":{"mimeType":"application/graphql","text":"{\"query\":\"query {\\n\\tplatform(order:{name: ASC}){\\n\\t\\tname\\n\\t\\tid\\n\\t\\tcommands{\\n\\t\\t\\tcommandLine\\n\\t\\t}\\n\\t}\\n}\"}"},"parameters":[],"headers":[{"name":"Content-Type","value":"application/json","id":"pair_98cc5411cc59446bbeecad6a4e02ed93"}],"authentication":{},"metaSortKey":-1645802004521,"isPrivate":false,"settingStoreCookies":true,"settingSendCookies":true,"settingDisableRenderRequestBody":false,"settingEncodeUrl":true,"settingRebuildPath":true,"settingFollowRedirects":"global","_type":"request"},{"_id":"fld_9b1cc478b82d411b9b158e465f5c7ae0","parentId":"wrk_d5da133116394facbc3bb22547468034","modified":1645896695392,"created":1645896695392,"name":"Queries","description":"","environment":{},"environmentPropertyOrder":null,"metaSortKey":-1645896695392,"_type":"request_group"},{"_id":"wrk_d5da133116394facbc3bb22547468034","parentId":null,"modified":1645732043801,"created":1645732043801,"name":"GraphQL Practice","description":"","scope":"collection","_type":"workspace"},{"_id":"req_f22ca899bb4c4b7ab267527eca355216","parentId":"fld_9b1cc478b82d411b9b158e465f5c7ae0","modified":1645896705194,"created":1645758701656,"url":"localhost:5157/graphql","name":"Parallel Platforms","description":"","method":"POST","body":{"mimeType":"application/graphql","text":"{\"query\":\"query {\\n\\ta: platform {\\n\\t\\tid\\n\\t\\tname\\n\\t}\\n\\tb: platform {\\n\\t\\tid\\n\\t\\tname\\n\\t}\\n\\tc: platform {\\n\\t\\tid\\n\\t\\tname\\n\\t}\\n\\td: platform {\\n\\t\\tid\\n\\t\\tname\\n\\t}\\n}\\n\"}"},"parameters":[],"headers":[{"name":"Content-Type","value":"application/json","id":"pair_de6cfa9c3a5645608f95e9e246c50248"}],"authentication":{},"metaSortKey":-1645802004514.75,"isPrivate":false,"settingStoreCookies":true,"settingSendCookies":true,"settingDisableRenderRequestBody":false,"settingEncodeUrl":true,"settingRebuildPath":true,"settingFollowRedirects":"global","_type":"request"},{"_id":"req_e986e6672c3347c7b63300ddbcf7523b","parentId":"fld_9b1cc478b82d411b9b158e465f5c7ae0","modified":1645896704229,"created":1645759966012,"url":"localhost:5157/graphql","name":"Get Platforms and Commands","description":"","method":"POST","body":{"mimeType":"application/graphql","text":"{\"query\":\"query {\\n\\tplatform {\\n\\t\\tid\\n\\t\\tname\\n\\t\\t commands{\\n\\t\\t\\tid\\n\\t\\t\\thowTo\\n\\t\\t\\tcommandLine\\n\\t\\t\\tplatformId\\n\\t\\t}\\n\\t}\\n}\\n\"}"},"parameters":[],"headers":[{"name":"Content-Type","value":"application/json","id":"pair_2718634243344b00abf71db1b56bc68b"}],"authentication":{},"metaSortKey":-1645802004508.5,"isPrivate":false,"settingStoreCookies":true,"settingSendCookies":true,"settingDisableRenderRequestBody":false,"settingEncodeUrl":true,"settingRebuildPath":true,"settingFollowRedirects":"global","_type":"request"},{"_id":"req_843fa4308cfd4707be4997eab799bf26","parentId":"fld_9b1cc478b82d411b9b158e465f5c7ae0","modified":1645896711148,"created":1645743757035,"url":"localhost:5157/graphql","name":"GetPlatforms","description":"","method":"POST","body":{"mimeType":"application/graphql","text":"{\"query\":\"query {\\n\\tplatform {\\n\\t\\tid\\n\\t\\tname\\n\\t\\tcommands{\\n\\t\\t\\tcommandLine\\n\\t\\t\\thowTo\\n\\t\\t}\\n\\t}\\n}\\n\"}"},"parameters":[{"id":"pair_f0cc3a286e2f4e618f2777caf7575fa8","name":"","value":"","description":""}],"headers":[{"name":"Content-Type","value":"application/json","id":"pair_471b9e54d8974fd08ad825a0f70a4203"}],"authentication":{},"metaSortKey":-1645802004502.25,"isPrivate":false,"settingStoreCookies":true,"settingSendCookies":true,"settingDisableRenderRequestBody":false,"settingEncodeUrl":true,"settingRebuildPath":true,"settingFollowRedirects":"global","_type":"request"},{"_id":"req_a53950a5819f47749f77532db8490b43","parentId":"fld_9b1cc478b82d411b9b158e465f5c7ae0","modified":1645896703267,"created":1645760794387,"url":"localhost:5157/graphql","name":"GetCommands","description":"","method":"POST","body":{"mimeType":"application/graphql","text":"{\"query\":\"query {\\n\\tcommand {\\n\\t\\thowTo\\n\\t\\tcommandLine\\n\\t\\tplatform {\\n\\t\\t\\tname\\n\\t\\t\\tid\\n\\t\\t}\\n\\t}\\n}\\n\"}"},"parameters":[],"headers":[{"name":"Content-Type","value":"application/json","id":"pair_ac7036e254f8445aa7e76693ecc04ce6"}],"authentication":{},"metaSortKey":-1645802004496,"isPrivate":false,"settingStoreCookies":true,"settingSendCookies":true,"settingDisableRenderRequestBody":false,"settingEncodeUrl":true,"settingRebuildPath":true,"settingFollowRedirects":"global","_type":"request"},{"_id":"req_21a36dc4f58e4752a925fccc56e9e06d","parentId":"fld_9b1cc478b82d411b9b158e465f5c7ae0","modified":1645896702101,"created":1645801568137,"url":"localhost:5157/graphql","name":"Filter Query","description":"","method":"POST","body":{"mimeType":"application/graphql","text":"{\"query\":\"query{\\n\\tcommand(where: {platformId: {eq:1 }}){\\n\\t\\tid\\n\\t\\tplatform{\\n\\t\\t\\tname\\n\\t\\t\\tid\\n\\t\\t}\\n\\t\\tcommandLine\\n\\t\\thowTo\\n\\t}\\n}\"}"},"parameters":[],"headers":[{"name":"Content-Type","value":"application/json","id":"pair_29a90f42e9214e57a0cc379f04e5c25f"}],"authentication":{},"metaSortKey":-1645802004471,"isPrivate":false,"settingStoreCookies":true,"settingSendCookies":true,"settingDisableRenderRequestBody":false,"settingEncodeUrl":true,"settingRebuildPath":true,"settingFollowRedirects":"global","_type":"request"},{"_id":"req_11c2b225ceb14571bb146c62358ed33c","parentId":"fld_47f9ffa9a5a44570a10e1ad2823d7bef","modified":1645897210731,"created":1645896620062,"url":"localhost:5157/graphql","name":"Add Platform","description":"","method":"POST","body":{"mimeType":"application/graphql","text":"{\"query\":\"mutation {\\n\\taddPlatform(input: { name: \\\"Windows baby\\\" }) {\\n\\t\\tplatform {\\n\\t\\t\\tid\\n\\t\\t\\tname\\n\\t\\t}\\n\\t}\\n}\\n\"}"},"parameters":[],"headers":[{"name":"Content-Type","value":"application/json","id":"pair_1434bc0e8c6a42f3831bb05f214cbb23"}],"authentication":{},"metaSortKey":-1645896620062,"isPrivate":false,"settingStoreCookies":true,"settingSendCookies":true,"settingDisableRenderRequestBody":false,"settingEncodeUrl":true,"settingRebuildPath":true,"settingFollowRedirects":"global","_type":"request"},{"_id":"fld_47f9ffa9a5a44570a10e1ad2823d7bef","parentId":"wrk_d5da133116394facbc3bb22547468034","modified":1645894367759,"created":1645894367759,"name":"Mutations","description":"","environment":{},"environmentPropertyOrder":null,"metaSortKey":-1645894367759,"_type":"request_group"},{"_id":"req_5639bb9a14cb406999b18a35eec15604","parentId":"fld_47f9ffa9a5a44570a10e1ad2823d7bef","modified":1645896624153,"created":1645894373654,"url":"localhost:5157/graphql","name":"Add COmmand","description":"","method":"POST","body":{"mimeType":"application/graphql","text":"{\"query\":\"mutation {\\n\\taddCommand(input: {\\n\\t\\thowTo:\\\"list directory\\\"\\n\\t\\tcommandLine:\\\"cd\\\"\\n\\t\\tplatformId:2\\n\\t})\\n\\t{command{\\n\\t\\tid\\n\\t\\thowTo\\n\\t\\tcommandLine\\n\\t\\tplatform{\\n\\t\\t\\tname\\n\\t\\t}\\n\\t}}\\n}\\n\\t\"}"},"parameters":[],"headers":[{"name":"Content-Type","value":"application/json","id":"pair_4f7f62ba5f584d74aa5376f0646746f0"}],"authentication":{},"metaSortKey":-1645894373654,"isPrivate":false,"settingStoreCookies":true,"settingSendCookies":true,"settingDisableRenderRequestBody":false,"settingEncodeUrl":true,"settingRebuildPath":true,"settingFollowRedirects":"global","_type":"request"},{"_id":"env_9d37fc49f9dad8f55e98a8b99e38a33246219a8f","parentId":"wrk_d5da133116394facbc3bb22547468034","modified":1645748658090,"created":1645732043840,"name":"Base Environment","data":{},"dataPropertyOrder":{},"color":null,"isPrivate":false,"metaSortKey":1645732043840,"_type":"environment"},{"_id":"jar_9d37fc49f9dad8f55e98a8b99e38a33246219a8f","parentId":"wrk_d5da133116394facbc3bb22547468034","modified":1645732043846,"created":1645732043846,"name":"Default Jar","cookies":[],"_type":"cookie_jar"},{"_id":"spc_69b1b3db8a054044a4d9ffc1c5662b69","parentId":"wrk_d5da133116394facbc3bb22547468034","modified":1645732043825,"created":1645732043825,"fileName":"GraphQL Practice","contents":"","contentType":"yaml","_type":"api_spec"}]}